<?xml version="1.0" encoding="utf-8"?>
<LanguageData>

  <VGE_GravshipLocker.label>armário de gravinave</VGE_GravshipLocker.label>
  <VGE_GravshipLocker.description>Um armário montado na parede para gravinaves. É principalmente destinado a maximizar o espaço, mas é ligeiramente menos eficiente para armazenamento do que uma prateleira típica.</VGE_GravshipLocker.description>

  <VGE_GravshipBunkBed.label>beliche de gravinave</VGE_GravshipBunkBed.label>
  <VGE_GravshipBunkBed.description>Uma beliche projetada para gravinaves. Economiza espaço, mas oferece menor conforto e eficácia de descanso.</VGE_GravshipBunkBed.description>

  <VGE_GravshipLight.label>luz de gravinave</VGE_GravshipLight.label>
  <VGE_GravshipLight.description>Uma luz pequena e brilhante para gravinaves. Não consome energia da rede elétrica principal. Em vez disso, ela consome energia diretamente do motor gravitacional.</VGE_GravshipLight.description>

  <VGE_GravshipCommsConsole.label>console de comunicações de gravinave</VGE_GravshipCommsConsole.label>
  <VGE_GravshipCommsConsole.description>Um console de comunicações eficiente em termos de espaço, projetado para uso a bordo de gravinaves. Ele consome energia diretamente do motor gravitacional.</VGE_GravshipCommsConsole.description>

  <VGE_SealantGoop.label>massa selante</VGE_SealantGoop.label>
  <VGE_SealantGoop.description>Um grumo de massa selante pegajosa e de endurecimento rápido. Usado para tapar rapidamente brechas no casco em um aperto.</VGE_SealantGoop.description>

</LanguageData>