<?xml version="1.0" encoding="utf-8"?>
<LanguageData>

  <VFEC_EquipShield.reportString>equipando TargetA.</VFEC_EquipShield.reportString>

  <VFEC_LeaveMap.reportString>saindo.</VFEC_LeaveMap.reportString>

  <VEF_CustomizeItem.reportString>personalizando TargetA.</VEF_CustomizeItem.reportString>

  <KCSG_GoToPassage.reportString>entrando TargetA.</KCSG_GoToPassage.reportString>

  <VEF_UseDoorTeleporter.reportString>usando TargetA para se teletransportar para TargetB</VEF_UseDoorTeleporter.reportString>

  <VFE_Loot.reportString>saqueando TargetA.</VFE_Loot.reportString>

  <VFE_StudyBuilding.reportString>estudando TargetA.</VFE_StudyBuilding.reportString>

  <VEF_RefuelSecondary.reportString>reabastecendo TargetA com munição.</VEF_RefuelSecondary.reportString>

</LanguageData>