<?xml version="1.0" encoding="UTF-8"?>
<LanguageData>
  
  <VRE_Allison.label>Allison</VRE_Allison.label>
  
  <VRE_Basset.label>Basset</VRE_Basset.label>
  
  <VRE_Bill.label>Bill</VRE_Bill.label>
  
  <VRE_Boswell.label>Boswell</VRE_Boswell.label>
  
  <VRE_Hays.label>Hays</VRE_Hays.label>
  
  <VRE_Hickock.label>Hickock</VRE_Hickock.label>
  
  <VRE_Holliday.label>Holliday</VRE_Holliday.label>
  
  <VRE_Materson.label>Materson</VRE_Materson.label>
  
  <VRE_Morgan.label>Morgan</VRE_Morgan.label>
  
  <VRE_Pat.label>Pat</VRE_Pat.label>
  
  <VRE_Virgil.label>Virgil</VRE_Virgil.label>
  
</LanguageData>