<?xml version="1.0" encoding="utf-8" ?>
<LanguageData>

  <VGE_Comet.label>cometa</VGE_Comet.label>
  <VGE_Comet.letterLabel>cometa</VGE_Comet.letterLabel>

  <VGE_SpaceDebris.label>detritos espaciais</VGE_SpaceDebris.label>
  <VGE_SpaceDebris.letterLabel>Detritos espaciais</VGE_SpaceDebris.letterLabel>
  <VGE_SpaceDebris.letterText>Uma nuvem à deriva de destroços antigos cruzou nossa rota de voo. Pedaços de metal e sucata passam pela nave. Alguns vão errar, outros podem não.\n\nOs detritos passarão por nós em cerca de 12 horas.</VGE_SpaceDebris.letterText>

  <VGE_AsteroidShower.label>chuva de asteroides</VGE_AsteroidShower.label>
  <VGE_AsteroidShower.letterLabel>Chuva de asteroides</VGE_AsteroidShower.letterLabel>

  <VGE_DustCloud.label>nuvem de poeira</VGE_DustCloud.label>
  <VGE_DustCloud.letterLabel>Nuvem de poeira</VGE_DustCloud.letterLabel>

</LanguageData>