<?xml version="1.0" encoding="utf-8"?>
<LanguageData>

	<Bionics.generalRules.rulesStrings>
		<li>subject_story>estudou vídeos em câmera lenta do movimento humano para criar melhores próteses biônicas</subject_story>
		<li>subject_story>se voluntariou para ter várias próteses biônicas implantadas, acabando mais como máquina do que como humano</subject_story>
		<li>subject_gerund>construindo próteses biônicas</subject_gerund>
		<li>subject_gerund>utilizando partes do corpo biônicas</subject_gerund>
	</Bionics.generalRules.rulesStrings>

	<SniperTurret.generalRules.rulesStrings>
		<li>subject>torretas de precisão</subject>
		<li>subject_story>liderou a limpeza após a guerra, recolhendo projéteis de urânio empobrecido radioativo da linha de frente</subject_story>
		<li>subject_story>viu uma torreta atirar diretamente através de um mecanoide de assalto e precisou entender como</subject_story>
		<li>subject_story>pesquisou os efeitos da densidade da munição na armadura</subject_story>
		<li>subject_gerund>construindo torretas de precisão</subject_gerund>
	</SniperTurret.generalRules.rulesStrings>

	<RocketswarmLauncher.generalRules.rulesStrings>
		<li>subject>lançadores de enxame de foguetes</subject>
		<li>subject_story>testemunhou o uso de lançadores de enxame de foguetes contra alvos civis</subject_story>
		<li>subject_story>construiu defesas de último recurso, incluindo armadilhas e lançadores, caso o assentamento fosse ameaçado</subject_story>
		<li>subject_story>começou construindo foguetes primitivos para alcançar o espaço, mas a alta taxa de falha levou-os a serem reaproveitados como armas</subject_story>
		<li>subject_gerund>construindo lançadores de enxame de foguetes</subject_gerund>
	</RocketswarmLauncher.generalRules.rulesStrings>

	<li>subject>multianálise</subject>
	<li>subject_story>automatizou um laboratório de pesquisa</subject_story>
	<li>subject_story>desvendou os segredos transespectrais do universo</subject_story>
	<li>subject_story>ajudou a identificar novos isótopos estáveis</subject_story>
	<li>subject_gerund>construindo multianalisadores</subject_gerund>

	<li>subject>monitoramento de sinais vitais</subject>
	<li>subject_story>lutou num hospital superlotado e jurou trabalhar por mudança</subject_story>
	<li>subject_story>cuidou de um sobrevivente de mundo de vidro para que recuperasse a saúde</subject_story>
	<li>subject_story>monitorou a ala de isolamento remotamente, enviando mecanoides para tratamentos</subject_story>
	<li>subject_gerund>monitorando sinais vitais</subject_gerund>
	<li>subject_gerund>construindo monitores de sinais vitais</subject_gerund>

	<li>subject>bancadas de fabricação de alta tecnologia</subject>
	<li>subject_story>passou muitos anos fabricando componentes avançados, para construir bancadas de fabricação e fabricar mais componentes avançados</subject_story>
	<li>subject_story>trocou tudo para construir uma única bancada de fabricação</subject_story>
	<li>subject_story>construiu maravilhas tecnológicas que os aldeões feriais adoravam como magia</subject_story>
	<li>subject_gerund>construindo projetos de alta tecnologia</subject_gerund>
	<li>subject_gerund>construindo estações de fabricação de alta tecnologia</subject_gerund>

	<li>subject>fabricação de componentes avançados</subject>
	<li>subject_story>trocou componentes avançados com habitantes de RimWorld desesperados</subject_story>
	<li>subject_story>aprendeu os segredos da fabricação de componentes avançados e morreu sem os revelar</subject_story>
	<li>subject_story>recuou perante o custo extremo de fabricar componentes avançados e escolheu um estilo de vida mais simples</subject_story>
	<li>subject_gerund>fabricando componentes avançados</subject_gerund>

	<li>subject>criossono</subject>
	<li>subject_story>pretendeu testar um protótipo de cápsula de criossono e acordou uma geração depois, sozinho</subject_story>
	<li>subject_story>sentenciou o pior criminoso do sistema a criossono indefinido em vez de morte</subject_story>
	<li>subject_story>usou uma cápsula de criossono para suspender os doentes terminais, para que pudessem ver os seus filhos depois de crescidos</subject_story>
	<li>subject_gerund>construindo cápsulas de criossono</subject_gerund>
	<li>subject_gerund>induzindo criossono</subject_gerund>

	<li>subject>armadura de reconhecimento</subject>
	<li>subject_story>liderou os batedores rebeldes contra as forças Imperiais, até ser capturado</subject_story>
	<li>subject_story>fabricou uma armadura motorizada leve e resiliente o suficiente para que os utilizadores de martelos se aproximassem do inimigo</subject_story>
	<li>subject_story>pretendeu armadura de reconhecimento mais para caçadores do que para soldados. Vendeu bem, independentemente</subject_story>
	<li>subject_gerund>fabricando armadura de reconhecimento</subject_gerund>
	<li>subject_gerund>reduzindo o peso da armadura</subject_gerund>

	<li>subject>armadura naval</subject>
	<li>subject_story>foi empregado pelas tropas de choque para manter a armadura deles</subject_story>
	<li>subject_story>testou a armadura caminhando, desarmado, por uma aldeia feral hostil sem receber um arranhão</subject_story>
	<li>subject_story>pretendeu a armadura como proteção contra o clima hostil do planeta, mas funcionou bem contra os piratas também</subject_story>
	<li>subject_gerund>construindo armadura de tropa de choque</subject_gerund>
	<li>subject_gerund>construindo armadura naval</subject_gerund>
	<li>subject_gerund>construindo armadura avançada de uso geral</subject_gerund>

	<li>subject>munições de pulso</subject>
	<li>subject_story>estudou monorails de mundos brilhantes e modificou a tecnologia para armas</subject_story>
	<li>subject_story>matou um rastreador mecânico "kiting-o" (usando a tática de kiting) com uma lança de carga</subject_story>
	<li>subject_story>aprendeu a imbuir munição de espingarda com carga retida, aumentando drasticamente a sua letalidade</subject_story>
	<li>subject_gerund>construindo munições de pulso</subject_gerund>
	<li>subject_gerund>utilizando munições de pulso</subject_gerund>

	<li>subject>prótese biônica</subject>
	<li>subject_story>trabalhou principalmente com soldados desfigurados, fabricando elementos faciais biônicos personalizados para que pudessem retornar aos seus entes queridos</subject_story>
	<li>subject_story>estudou vídeos em câmera lenta de movimento humano para fabricar melhor próteses biônicas</subject_story>
	<li>subject_story>ofereceu-se para ter as várias próteses biônicas protótipo implantadas, tornando-se mais máquina do que homem</subject_story>
	<li>subject_gerund>construindo próteses biônicas</subject_gerund>
	<li>subject_gerund>utilizando partes do corpo biônicas</subject_gerund>

	<li>subject>torretas de precisão</subject>
	<li>subject_story>liderou a limpeza após a guerra, recolhendo projéteis de urânio empobrecido radioativo gastos da linha de frente</subject_story>
	<li>subject_story>viu uma torreta atirar diretamente através de um mecanoide de assalto e precisou de entender como</subject_story>
	<li>subject_story>pesquisou os efeitos da densidade da munição na armadura</subject_story>
	<li>subject_gerund>construindo torretas de precisão</subject_gerund>

	<li>subject>lançadores de enxame de foguetes</subject>
	<li>subject_story>testemunhou o uso de lança-foguetes contra alvos civis</subject_story>
	<li>subject_story>construiu defesas de última hora, incluindo armadilhas e lançadores, caso o assentamento fosse ameaçado</subject_story>
	<li>subject_story>começou por construir foguetes primitivos para alcançar o espaço, mas a alta taxa de falha levou a que fossem reaproveitados como armas</subject_story>
	<li>subject_gerund>construindo lançadores de enxame de foguetes</subject_gerund>

</LanguageData>